README.rst
setup.cfg
setup.py
asynccli/__init__.py
asynccli/app.py
asynccli/arguments.py
asynccli/cli.py
asynccli.egg-info/PKG-INFO
asynccli.egg-info/SOURCES.txt
asynccli.egg-info/dependency_links.txt
asynccli.egg-info/top_level.txt
tests/__init__.py
tests/test_calculator.py
tests/test_division_calculator.py
tests/test_hello_world.py
tests/test_initial.py