Metadata-Version: 1.1
Name: asynccli
Version: 0.1.2
Summary: A CLI framework based on asyncio
Home-page: https://github.com/ahopkins/asynccli
Author: Adam Hopkins
Author-email: admhpkns@gmail.com
License: UNKNOWN
Platform: UNKNOWN
Classifier: Development Status :: 4 - Beta
Classifier: Framework :: AsyncIO
Classifier: Intended Audience :: Developers
Classifier: License :: OSI Approved :: Mozilla Public License 2.0 (MPL 2.0)
Classifier: Programming Language :: Python
Classifier: Programming Language :: Python :: 3
Classifier: Programming Language :: Python :: 3.5
Classifier: Programming Language :: Python :: 3.6
